preimport/__init__.py
preimport/core.py
preimport-1.1.6.dist-info/LICENSE
preimport-1.1.6.dist-info/METADATA
preimport-1.1.6.dist-info/WHEEL
preimport-1.1.6.dist-info/top_level.txt
preimport-1.1.6.dist-info/RECORD
